[{"naam":"Tom Remeeus","meetsessies":[{"datum":"2015-11-04T12:37:26.4114749+01:00","leeftijd":20,"gewicht":92,"session":[{"pulse":0,"rpm":16,"speed":57,"distance":0,"requestedPower":25,"energy":0,"actualPower":25,"time":59},{"pulse":0,"rpm":52,"speed":185,"distance":0,"requestedPower":25,"energy":0,"actualPower":25,"time":58},{"pulse":0,"rpm":52,"speed":185,"distance":0,"requestedPower":25,"energy":0,"actualPower":25,"time":57},{"pulse":0,"rpm":73,"speed":259,"distance":0,"requestedPower":25,"energy":0,"actualPower":25,"time":56},{"pulse":0,"rpm":73,"speed":259,"distance":0,"requestedPower":25,"energy":0,"actualPower":25,"time":55},{"pulse":0,"rpm":80,"speed":284,"distance":0,"requestedPower":25,"energy":0,"actualPower":25,"time":54},{"pulse":0,"rpm":80,"speed":284,"distance":0,"requestedPower":25,"energy":0,"actualPower":25,"time":53},{"pulse":0,"rpm":82,"speed":291,"distance":0,"requestedPower":45,"energy":0,"actualPower":25,"time":52},{"pulse":0,"rpm":82,"speed":291,"distance":0,"requestedPower":45,"energy":1,"actualPower":45,"time":51},{"pulse":0,"rpm":78,"speed":277,"distance":0,"requestedPower":45,"energy":1,"actualPower":45,"time":50},{"pulse":0,"rpm":78,"speed":277,"distance":0,"requestedPower":45,"energy":1,"actualPower":45,"time":49},{"pulse":0,"rpm":76,"speed":270,"distance":0,"requestedPower":45,"energy":1,"actualPower":45,"time":48},{"pulse":0,"rpm":76,"speed":270,"distance":0,"requestedPower":45,"energy":1,"actualPower":45,"time":47},{"pulse":0,"rpm":76,"speed":270,"distance":1,"requestedPower":45,"energy":1,"actualPower":45,"time":46},{"pulse":0,"rpm":76,"speed":270,"distance":1,"requestedPower":70,"energy":2,"actualPower":45,"time":45},{"pulse":0,"rpm":77,"speed":273,"distance":1,"requestedPower":70,"energy":2,"actualPower":70,"time":44},{"pulse":0,"rpm":77,"speed":273,"distance":1,"requestedPower":70,"energy":2,"actualPower":70,"time":43},{"pulse":0,"rpm":76,"speed":270,"distance":1,"requestedPower":70,"energy":3,"actualPower":70,"time":42},{"pulse":0,"rpm":76,"speed":270,"distance":1,"requestedPower":70,"energy":3,"actualPower":70,"time":41},{"pulse":0,"rpm":77,"speed":273,"distance":1,"requestedPower":70,"energy":3,"actualPower":70,"time":40},{"pulse":0,"rpm":77,"speed":273,"distance":1,"requestedPower":70,"energy":3,"actualPower":70,"time":39},{"pulse":0,"rpm":77,"speed":273,"distance":1,"requestedPower":90,"energy":4,"actualPower":70,"time":38},{"pulse":0,"rpm":73,"speed":259,"distance":1,"requestedPower":90,"energy":4,"actualPower":90,"time":37},{"pulse":0,"rpm":73,"speed":259,"distance":1,"requestedPower":90,"energy":4,"actualPower":90,"time":36},{"pulse":0,"rpm":71,"speed":252,"distance":1,"requestedPower":90,"energy":5,"actualPower":90,"time":35},{"pulse":0,"rpm":71,"speed":252,"distance":1,"requestedPower":90,"energy":5,"actualPower":90,"time":34},{"pulse":0,"rpm":70,"speed":249,"distance":1,"requestedPower":90,"energy":5,"actualPower":90,"time":33},{"pulse":0,"rpm":70,"speed":249,"distance":2,"requestedPower":90,"energy":6,"actualPower":90,"time":32},{"pulse":0,"rpm":71,"speed":252,"distance":2,"requestedPower":115,"energy":6,"actualPower":90,"time":31},{"pulse":0,"rpm":71,"speed":252,"distance":2,"requestedPower":115,"energy":7,"actualPower":115,"time":30},{"pulse":0,"rpm":71,"speed":252,"distance":2,"requestedPower":115,"energy":7,"actualPower":115,"time":29},{"pulse":0,"rpm":71,"speed":252,"distance":2,"requestedPower":115,"energy":8,"actualPower":115,"time":28},{"pulse":0,"rpm":73,"speed":259,"distance":2,"requestedPower":115,"energy":8,"actualPower":115,"time":27},{"pulse":0,"rpm":73,"speed":259,"distance":2,"requestedPower":115,"energy":8,"actualPower":115,"time":26},{"pulse":0,"rpm":72,"speed":256,"distance":2,"requestedPower":115,"energy":9,"actualPower":115,"time":25},{"pulse":0,"rpm":72,"speed":256,"distance":2,"requestedPower":135,"energy":9,"actualPower":115,"time":24},{"pulse":0,"rpm":74,"speed":263,"distance":2,"requestedPower":135,"energy":10,"actualPower":135,"time":23},{"pulse":0,"rpm":74,"speed":263,"distance":2,"requestedPower":135,"energy":10,"actualPower":135,"time":22},{"pulse":0,"rpm":75,"speed":266,"distance":2,"requestedPower":135,"energy":11,"actualPower":135,"time":21},{"pulse":0,"rpm":75,"speed":266,"distance":2,"requestedPower":135,"energy":12,"actualPower":135,"time":20},{"pulse":0,"rpm":74,"speed":263,"distance":2,"requestedPower":135,"energy":12,"actualPower":135,"time":19},{"pulse":0,"rpm":74,"speed":263,"distance":3,"requestedPower":135,"energy":13,"actualPower":135,"time":18},{"pulse":0,"rpm":74,"speed":263,"distance":3,"requestedPower":155,"energy":13,"actualPower":135,"time":17},{"pulse":0,"rpm":74,"speed":263,"distance":3,"requestedPower":155,"energy":14,"actualPower":155,"time":16},{"pulse":0,"rpm":74,"speed":263,"distance":3,"requestedPower":155,"energy":14,"actualPower":155,"time":15},{"pulse":0,"rpm":74,"speed":263,"distance":3,"requestedPower":155,"energy":15,"actualPower":155,"time":14},{"pulse":0,"rpm":70,"speed":249,"distance":3,"requestedPower":155,"energy":16,"actualPower":155,"time":13},{"pulse":0,"rpm":70,"speed":249,"distance":3,"requestedPower":155,"energy":16,"actualPower":155,"time":12},{"pulse":0,"rpm":74,"speed":263,"distance":3,"requestedPower":155,"energy":17,"actualPower":155,"time":11},{"pulse":0,"rpm":74,"speed":263,"distance":3,"requestedPower":180,"energy":17,"actualPower":155,"time":10},{"pulse":0,"rpm":75,"speed":266,"distance":3,"requestedPower":180,"energy":18,"actualPower":180,"time":9},{"pulse":0,"rpm":75,"speed":266,"distance":3,"requestedPower":180,"energy":19,"actualPower":180,"time":8},{"pulse":0,"rpm":75,"speed":266,"distance":3,"requestedPower":180,"energy":20,"actualPower":180,"time":7},{"pulse":0,"rpm":75,"speed":266,"distance":3,"requestedPower":180,"energy":20,"actualPower":180,"time":6},{"pulse":0,"rpm":75,"speed":266,"distance":3,"requestedPower":180,"energy":21,"actualPower":180,"time":5},{"pulse":0,"rpm":75,"speed":266,"distance":4,"requestedPower":180,"energy":22,"actualPower":180,"time":4},{"pulse":0,"rpm":75,"speed":266,"distance":4,"requestedPower":200,"energy":23,"actualPower":180,"time":3},{"pulse":0,"rpm":68,"speed":241,"distance":4,"requestedPower":200,"energy":23,"actualPower":200,"time":2},{"pulse":0,"rpm":68,"speed":241,"distance":4,"requestedPower":200,"energy":24,"actualPower":200,"time":1}]},{"datum":"2015-11-04T12:55:24.7235767+01:00","leeftijd":20,"gewicht":92,"session":[{"pulse":172,"rpm":51,"speed":181,"distance":0,"requestedPower":25,"energy":0,"actualPower":21,"time":299},{"pulse":172,"rpm":51,"speed":181,"distance":0,"requestedPower":25,"energy":0,"actualPower":25,"time":298},{"pulse":172,"rpm":61,"speed":217,"distance":0,"requestedPower":25,"energy":0,"actualPower":25,"time":297},{"pulse":172,"rpm":61,"speed":217,"distance":0,"requestedPower":25,"energy":0,"actualPower":25,"time":296},{"pulse":172,"rpm":62,"speed":220,"distance":0,"requestedPower":25,"energy":0,"actualPower":25,"time":295},{"pulse":171,"rpm":62,"speed":220,"distance":0,"requestedPower":25,"energy":0,"actualPower":25,"time":294},{"pulse":171,"rpm":65,"speed":231,"distance":0,"requestedPower":25,"energy":0,"actualPower":25,"time":293},{"pulse":171,"rpm":65,"speed":231,"distance":0,"requestedPower":25,"energy":0,"actualPower":25,"time":292},{"pulse":170,"rpm":68,"speed":241,"distance":0,"requestedPower":25,"energy":0,"actualPower":25,"time":291},{"pulse":170,"rpm":68,"speed":241,"distance":0,"requestedPower":25,"energy":1,"actualPower":25,"time":290},{"pulse":170,"rpm":73,"speed":259,"distance":0,"requestedPower":25,"energy":1,"actualPower":25,"time":289},{"pulse":170,"rpm":73,"speed":259,"distance":0,"requestedPower":25,"energy":1,"actualPower":25,"time":288},{"pulse":170,"rpm":75,"speed":266,"distance":0,"requestedPower":25,"energy":1,"actualPower":25,"time":287},{"pulse":166,"rpm":75,"speed":266,"distance":0,"requestedPower":25,"energy":1,"actualPower":25,"time":286},{"pulse":143,"rpm":74,"speed":263,"distance":0,"requestedPower":25,"energy":1,"actualPower":25,"time":285},{"pulse":143,"rpm":74,"speed":263,"distance":1,"requestedPower":25,"energy":1,"actualPower":25,"time":284},{"pulse":166,"rpm":74,"speed":263,"distance":1,"requestedPower":25,"energy":1,"actualPower":25,"time":283},{"pulse":143,"rpm":74,"speed":263,"distance":1,"requestedPower":25,"energy":1,"actualPower":25,"time":282},{"pulse":143,"rpm":77,"speed":273,"distance":1,"requestedPower":25,"energy":1,"actualPower":25,"time":281},{"pulse":143,"rpm":77,"speed":273,"distance":1,"requestedPower":25,"energy":2,"actualPower":25,"time":280},{"pulse":0,"rpm":80,"speed":284,"distance":1,"requestedPower":25,"energy":2,"actualPower":25,"time":279},{"pulse":0,"rpm":80,"speed":284,"distance":1,"requestedPower":25,"energy":2,"actualPower":25,"time":278},{"pulse":0,"rpm":78,"speed":277,"distance":1,"requestedPower":25,"energy":2,"actualPower":25,"time":277},{"pulse":0,"rpm":78,"speed":277,"distance":1,"requestedPower":25,"energy":2,"actualPower":25,"time":276},{"pulse":0,"rpm":76,"speed":270,"distance":1,"requestedPower":25,"energy":2,"actualPower":25,"time":275},{"pulse":0,"rpm":76,"speed":270,"distance":1,"requestedPower":25,"energy":2,"actualPower":25,"time":274},{"pulse":0,"rpm":82,"speed":291,"distance":1,"requestedPower":25,"energy":2,"actualPower":25,"time":273},{"pulse":0,"rpm":82,"speed":291,"distance":1,"requestedPower":25,"energy":2,"actualPower":25,"time":272},{"pulse":0,"rpm":80,"speed":284,"distance":2,"requestedPower":25,"energy":2,"actualPower":25,"time":271},{"pulse":0,"rpm":80,"speed":284,"distance":2,"requestedPower":25,"energy":3,"actualPower":25,"time":270},{"pulse":0,"rpm":80,"speed":284,"distance":2,"requestedPower":45,"energy":3,"actualPower":25,"time":269},{"pulse":0,"rpm":80,"speed":284,"distance":2,"requestedPower":45,"energy":3,"actualPower":45,"time":268},{"pulse":0,"rpm":80,"speed":284,"distance":2,"requestedPower":45,"energy":3,"actualPower":45,"time":267},{"pulse":0,"rpm":76,"speed":270,"distance":2,"requestedPower":45,"energy":3,"actualPower":45,"time":266},{"pulse":0,"rpm":76,"speed":270,"distance":2,"requestedPower":45,"energy":3,"actualPower":45,"time":265},{"pulse":0,"rpm":72,"speed":256,"distance":2,"requestedPower":45,"energy":4,"actualPower":45,"time":264},{"pulse":0,"rpm":72,"speed":256,"distance":2,"requestedPower":45,"energy":4,"actualPower":45,"time":263},{"pulse":0,"rpm":77,"speed":273,"distance":2,"requestedPower":45,"energy":4,"actualPower":45,"time":262},{"pulse":0,"rpm":77,"speed":273,"distance":2,"requestedPower":45,"energy":4,"actualPower":45,"time":261},{"pulse":0,"rpm":75,"speed":266,"distance":2,"requestedPower":45,"energy":4,"actualPower":45,"time":260},{"pulse":0,"rpm":75,"speed":266,"distance":2,"requestedPower":45,"energy":4,"actualPower":45,"time":259},{"pulse":0,"rpm":73,"speed":259,"distance":3,"requestedPower":45,"energy":5,"actualPower":45,"time":258},{"pulse":0,"rpm":73,"speed":259,"distance":3,"requestedPower":45,"energy":5,"actualPower":45,"time":257},{"pulse":0,"rpm":74,"speed":263,"distance":3,"requestedPower":45,"energy":5,"actualPower":45,"time":256},{"pulse":0,"rpm":74,"speed":263,"distance":3,"requestedPower":45,"energy":5,"actualPower":45,"time":255},{"pulse":0,"rpm":74,"speed":263,"distance":3,"requestedPower":45,"energy":5,"actualPower":45,"time":254},{"pulse":0,"rpm":74,"speed":263,"distance":3,"requestedPower":45,"energy":5,"actualPower":45,"time":253},{"pulse":0,"rpm":74,"speed":263,"distance":3,"requestedPower":45,"energy":6,"actualPower":45,"time":252},{"pulse":0,"rpm":74,"speed":263,"distance":3,"requestedPower":45,"energy":6,"actualPower":45,"time":251},{"pulse":0,"rpm":75,"speed":266,"distance":3,"requestedPower":45,"energy":6,"actualPower":45,"time":250},{"pulse":0,"rpm":75,"speed":266,"distance":3,"requestedPower":45,"energy":6,"actualPower":45,"time":249},{"pulse":0,"rpm":79,"speed":280,"distance":3,"requestedPower":45,"energy":6,"actualPower":45,"time":248},{"pulse":0,"rpm":79,"speed":280,"distance":3,"requestedPower":45,"energy":7,"actualPower":45,"time":247},{"pulse":0,"rpm":82,"speed":291,"distance":3,"requestedPower":45,"energy":7,"actualPower":45,"time":246},{"pulse":0,"rpm":82,"speed":291,"distance":4,"requestedPower":45,"energy":7,"actualPower":45,"time":245},{"pulse":0,"rpm":85,"speed":302,"distance":4,"requestedPower":45,"energy":7,"actualPower":45,"time":244},{"pulse":0,"rpm":85,"speed":302,"distance":4,"requestedPower":45,"energy":7,"actualPower":45,"time":243},{"pulse":0,"rpm":87,"speed":309,"distance":4,"requestedPower":45,"energy":7,"actualPower":45,"time":242},{"pulse":0,"rpm":87,"speed":309,"distance":4,"requestedPower":45,"energy":8,"actualPower":45,"time":241},{"pulse":0,"rpm":83,"speed":295,"distance":4,"requestedPower":45,"energy":8,"actualPower":45,"time":240},{"pulse":0,"rpm":83,"speed":295,"distance":4,"requestedPower":45,"energy":8,"actualPower":45,"time":239},{"pulse":0,"rpm":83,"speed":295,"distance":4,"requestedPower":70,"energy":8,"actualPower":45,"time":238},{"pulse":0,"rpm":72,"speed":256,"distance":4,"requestedPower":70,"energy":8,"actualPower":70,"time":237},{"pulse":0,"rpm":72,"speed":256,"distance":4,"requestedPower":70,"energy":9,"actualPower":70,"time":236},{"pulse":0,"rpm":61,"speed":217,"distance":4,"requestedPower":70,"energy":9,"actualPower":70,"time":235},{"pulse":0,"rpm":61,"speed":217,"distance":4,"requestedPower":70,"energy":9,"actualPower":70,"time":234},{"pulse":0,"rpm":39,"speed":138,"distance":4,"requestedPower":70,"energy":10,"actualPower":70,"time":233},{"pulse":0,"rpm":39,"speed":138,"distance":4,"requestedPower":70,"energy":10,"actualPower":70,"time":232},{"pulse":0,"rpm":15,"speed":53,"distance":4,"requestedPower":70,"energy":10,"actualPower":70,"time":231},{"pulse":0,"rpm":15,"speed":53,"distance":4,"requestedPower":70,"energy":10,"actualPower":70,"time":230},{"pulse":0,"rpm":22,"speed":78,"distance":4,"requestedPower":70,"energy":11,"actualPower":70,"time":229},{"pulse":0,"rpm":22,"speed":78,"distance":4,"requestedPower":70,"energy":11,"actualPower":70,"time":228},{"pulse":0,"rpm":28,"speed":99,"distance":4,"requestedPower":70,"energy":11,"actualPower":70,"time":227},{"pulse":0,"rpm":28,"speed":99,"distance":4,"requestedPower":70,"energy":12,"actualPower":70,"time":226},{"pulse":0,"rpm":37,"speed":131,"distance":5,"requestedPower":70,"energy":12,"actualPower":70,"time":225},{"pulse":0,"rpm":37,"speed":131,"distance":5,"requestedPower":70,"energy":12,"actualPower":70,"time":224},{"pulse":0,"rpm":46,"speed":163,"distance":5,"requestedPower":70,"energy":12,"actualPower":70,"time":223},{"pulse":0,"rpm":46,"speed":163,"distance":5,"requestedPower":70,"energy":13,"actualPower":70,"time":222},{"pulse":0,"rpm":50,"speed":178,"distance":5,"requestedPower":70,"energy":13,"actualPower":70,"time":221},{"pulse":0,"rpm":50,"speed":178,"distance":5,"requestedPower":70,"energy":13,"actualPower":70,"time":220},{"pulse":0,"rpm":50,"speed":178,"distance":5,"requestedPower":70,"energy":14,"actualPower":70,"time":219},{"pulse":0,"rpm":56,"speed":199,"distance":5,"requestedPower":70,"energy":14,"actualPower":70,"time":218},{"pulse":0,"rpm":56,"speed":199,"distance":5,"requestedPower":70,"energy":14,"actualPower":70,"time":217},{"pulse":0,"rpm":61,"speed":217,"distance":5,"requestedPower":70,"energy":14,"actualPower":70,"time":216},{"pulse":0,"rpm":61,"speed":217,"distance":5,"requestedPower":70,"energy":15,"actualPower":70,"time":215},{"pulse":0,"rpm":63,"speed":224,"distance":5,"requestedPower":70,"energy":15,"actualPower":70,"time":214},{"pulse":0,"rpm":63,"speed":224,"distance":5,"requestedPower":70,"energy":15,"actualPower":70,"time":213},{"pulse":79,"rpm":64,"speed":227,"distance":5,"requestedPower":70,"energy":15,"actualPower":70,"time":212},{"pulse":80,"rpm":64,"speed":227,"distance":5,"requestedPower":70,"energy":16,"actualPower":70,"time":211},{"pulse":80,"rpm":66,"speed":234,"distance":5,"requestedPower":70,"energy":16,"actualPower":70,"time":210},{"pulse":81,"rpm":66,"speed":234,"distance":5,"requestedPower":70,"energy":16,"actualPower":70,"time":209},{"pulse":82,"rpm":65,"speed":231,"distance":6,"requestedPower":70,"energy":17,"actualPower":70,"time":208},{"pulse":83,"rpm":65,"speed":231,"distance":6,"requestedPower":90,"energy":17,"actualPower":70,"time":207},{"pulse":83,"rpm":65,"speed":231,"distance":6,"requestedPower":90,"energy":17,"actualPower":90,"time":206},{"pulse":83,"rpm":65,"speed":231,"distance":6,"requestedPower":90,"energy":18,"actualPower":90,"time":205},{"pulse":82,"rpm":63,"speed":224,"distance":6,"requestedPower":90,"energy":18,"actualPower":90,"time":204},{"pulse":82,"rpm":63,"speed":224,"distance":6,"requestedPower":90,"energy":18,"actualPower":90,"time":203},{"pulse":81,"rpm":57,"speed":202,"distance":6,"requestedPower":90,"energy":19,"actualPower":90,"time":202},{"pulse":81,"rpm":57,"speed":202,"distance":6,"requestedPower":90,"energy":19,"actualPower":90,"time":201},{"pulse":80,"rpm":62,"speed":220,"distance":6,"requestedPower":90,"energy":19,"actualPower":90,"time":200},{"pulse":80,"rpm":62,"speed":220,"distance":6,"requestedPower":90,"energy":20,"actualPower":90,"time":199},{"pulse":81,"rpm":64,"speed":227,"distance":6,"requestedPower":90,"energy":20,"actualPower":90,"time":198},{"pulse":81,"rpm":64,"speed":227,"distance":6,"requestedPower":90,"energy":20,"actualPower":90,"time":197},{"pulse":81,"rpm":64,"speed":227,"distance":6,"requestedPower":90,"energy":21,"actualPower":90,"time":196},{"pulse":82,"rpm":64,"speed":227,"distance":6,"requestedPower":90,"energy":21,"actualPower":90,"time":195},{"pulse":82,"rpm":62,"speed":220,"distance":6,"requestedPower":90,"energy":22,"actualPower":90,"time":194},{"pulse":83,"rpm":62,"speed":220,"distance":6,"requestedPower":90,"energy":22,"actualPower":90,"time":193},{"pulse":83,"rpm":62,"speed":220,"distance":6,"requestedPower":90,"energy":22,"actualPower":90,"time":192},{"pulse":83,"rpm":62,"speed":220,"distance":7,"requestedPower":90,"energy":23,"actualPower":90,"time":191},{"pulse":83,"rpm":60,"speed":213,"distance":7,"requestedPower":90,"energy":23,"actualPower":90,"time":190},{"pulse":83,"rpm":60,"speed":213,"distance":7,"requestedPower":90,"energy":23,"actualPower":90,"time":189},{"pulse":83,"rpm":60,"speed":213,"distance":7,"requestedPower":90,"energy":24,"actualPower":90,"time":188},{"pulse":83,"rpm":62,"speed":220,"distance":7,"requestedPower":90,"energy":24,"actualPower":90,"time":187},{"pulse":83,"rpm":62,"speed":220,"distance":7,"requestedPower":90,"energy":24,"actualPower":90,"time":186},{"pulse":83,"rpm":62,"speed":220,"distance":7,"requestedPower":90,"energy":25,"actualPower":90,"time":185},{"pulse":83,"rpm":62,"speed":220,"distance":7,"requestedPower":90,"energy":25,"actualPower":90,"time":184},{"pulse":83,"rpm":63,"speed":224,"distance":7,"requestedPower":90,"energy":26,"actualPower":90,"time":183},{"pulse":83,"rpm":63,"speed":224,"distance":7,"requestedPower":90,"energy":26,"actualPower":90,"time":182},{"pulse":83,"rpm":65,"speed":231,"distance":7,"requestedPower":90,"energy":26,"actualPower":90,"time":181},{"pulse":83,"rpm":65,"speed":231,"distance":7,"requestedPower":90,"energy":27,"actualPower":90,"time":180},{"pulse":83,"rpm":59,"speed":209,"distance":7,"requestedPower":90,"energy":27,"actualPower":90,"time":179},{"pulse":83,"rpm":59,"speed":209,"distance":7,"requestedPower":90,"energy":27,"actualPower":90,"time":178},{"pulse":83,"rpm":61,"speed":217,"distance":7,"requestedPower":90,"energy":28,"actualPower":90,"time":177},{"pulse":83,"rpm":61,"speed":217,"distance":7,"requestedPower":115,"energy":28,"actualPower":90,"time":176},{"pulse":83,"rpm":64,"speed":227,"distance":8,"requestedPower":115,"energy":28,"actualPower":115,"time":175},{"pulse":83,"rpm":64,"speed":227,"distance":8,"requestedPower":115,"energy":29,"actualPower":115,"time":174},{"pulse":83,"rpm":62,"speed":220,"distance":8,"requestedPower":115,"energy":29,"actualPower":115,"time":173},{"pulse":83,"rpm":62,"speed":220,"distance":8,"requestedPower":115,"energy":30,"actualPower":115,"time":172},{"pulse":83,"rpm":55,"speed":195,"distance":8,"requestedPower":115,"energy":30,"actualPower":115,"time":171},{"pulse":83,"rpm":55,"speed":195,"distance":8,"requestedPower":115,"energy":31,"actualPower":115,"time":170},{"pulse":83,"rpm":55,"speed":195,"distance":8,"requestedPower":115,"energy":31,"actualPower":115,"time":169},{"pulse":83,"rpm":59,"speed":209,"distance":8,"requestedPower":115,"energy":32,"actualPower":115,"time":168},{"pulse":83,"rpm":59,"speed":209,"distance":8,"requestedPower":115,"energy":32,"actualPower":115,"time":167},{"pulse":84,"rpm":61,"speed":217,"distance":8,"requestedPower":115,"energy":33,"actualPower":115,"time":166},{"pulse":84,"rpm":61,"speed":217,"distance":8,"requestedPower":115,"energy":33,"actualPower":115,"time":165},{"pulse":84,"rpm":61,"speed":217,"distance":8,"requestedPower":115,"energy":34,"actualPower":115,"time":164},{"pulse":84,"rpm":61,"speed":217,"distance":8,"requestedPower":115,"energy":34,"actualPower":115,"time":163},{"pulse":84,"rpm":63,"speed":224,"distance":8,"requestedPower":115,"energy":34,"actualPower":115,"time":162},{"pulse":84,"rpm":63,"speed":224,"distance":8,"requestedPower":115,"energy":35,"actualPower":115,"time":161},{"pulse":84,"rpm":60,"speed":213,"distance":8,"requestedPower":115,"energy":35,"actualPower":115,"time":160},{"pulse":84,"rpm":60,"speed":213,"distance":8,"requestedPower":115,"energy":36,"actualPower":115,"time":159},{"pulse":84,"rpm":62,"speed":220,"distance":9,"requestedPower":115,"energy":36,"actualPower":115,"time":158},{"pulse":84,"rpm":62,"speed":220,"distance":9,"requestedPower":115,"energy":37,"actualPower":115,"time":157},{"pulse":84,"rpm":61,"speed":217,"distance":9,"requestedPower":115,"energy":37,"actualPower":115,"time":156},{"pulse":84,"rpm":61,"speed":217,"distance":9,"requestedPower":115,"energy":38,"actualPower":115,"time":155},{"pulse":84,"rpm":63,"speed":224,"distance":9,"requestedPower":115,"energy":38,"actualPower":115,"time":154},{"pulse":84,"rpm":63,"speed":224,"distance":9,"requestedPower":115,"energy":39,"actualPower":115,"time":153},{"pulse":84,"rpm":61,"speed":217,"distance":9,"requestedPower":115,"energy":39,"actualPower":115,"time":152},{"pulse":84,"rpm":61,"speed":217,"distance":9,"requestedPower":115,"energy":40,"actualPower":115,"time":151},{"pulse":86,"rpm":61,"speed":217,"distance":9,"requestedPower":115,"energy":40,"actualPower":115,"time":150},{"pulse":87,"rpm":61,"speed":217,"distance":9,"requestedPower":115,"energy":40,"actualPower":115,"time":149},{"pulse":87,"rpm":62,"speed":220,"distance":9,"requestedPower":115,"energy":41,"actualPower":115,"time":148},{"pulse":87,"rpm":62,"speed":220,"distance":9,"requestedPower":115,"energy":41,"actualPower":115,"time":147},{"pulse":87,"rpm":61,"speed":217,"distance":9,"requestedPower":115,"energy":42,"actualPower":115,"time":146},{"pulse":87,"rpm":61,"speed":217,"distance":9,"requestedPower":135,"energy":42,"actualPower":115,"time":145},{"pulse":87,"rpm":61,"speed":217,"distance":9,"requestedPower":135,"energy":43,"actualPower":135,"time":144},{"pulse":87,"rpm":61,"speed":217,"distance":9,"requestedPower":135,"energy":43,"actualPower":135,"time":143},{"pulse":87,"rpm":60,"speed":213,"distance":9,"requestedPower":135,"energy":44,"actualPower":135,"time":142},{"pulse":87,"rpm":60,"speed":213,"distance":10,"requestedPower":135,"energy":44,"actualPower":135,"time":141},{"pulse":87,"rpm":59,"speed":209,"distance":10,"requestedPower":135,"energy":45,"actualPower":135,"time":140},{"pulse":87,"rpm":59,"speed":209,"distance":10,"requestedPower":135,"energy":46,"actualPower":135,"time":139},{"pulse":87,"rpm":59,"speed":209,"distance":10,"requestedPower":135,"energy":46,"actualPower":135,"time":138},{"pulse":88,"rpm":60,"speed":213,"distance":10,"requestedPower":135,"energy":47,"actualPower":135,"time":137},{"pulse":87,"rpm":60,"speed":213,"distance":10,"requestedPower":135,"energy":47,"actualPower":135,"time":136},{"pulse":88,"rpm":58,"speed":206,"distance":10,"requestedPower":135,"energy":48,"actualPower":135,"time":135},{"pulse":88,"rpm":58,"speed":206,"distance":10,"requestedPower":135,"energy":48,"actualPower":135,"time":134},{"pulse":89,"rpm":61,"speed":217,"distance":10,"requestedPower":135,"energy":49,"actualPower":135,"time":133},{"pulse":89,"rpm":61,"speed":217,"distance":10,"requestedPower":135,"energy":49,"actualPower":135,"time":132},{"pulse":89,"rpm":45,"speed":160,"distance":10,"requestedPower":135,"energy":50,"actualPower":135,"time":131},{"pulse":89,"rpm":45,"speed":160,"distance":10,"requestedPower":135,"energy":50,"actualPower":135,"time":130},{"pulse":89,"rpm":45,"speed":160,"distance":10,"requestedPower":135,"energy":50,"actualPower":135,"time":129},{"pulse":90,"rpm":0,"speed":0,"distance":10,"requestedPower":135,"energy":51,"actualPower":0,"time":128},{"pulse":89,"rpm":46,"speed":163,"distance":10,"requestedPower":135,"energy":52,"actualPower":42,"time":127},{"pulse":90,"rpm":57,"speed":202,"distance":10,"requestedPower":135,"energy":53,"actualPower":72,"time":126},{"pulse":90,"rpm":57,"speed":202,"distance":10,"requestedPower":135,"energy":53,"actualPower":102,"time":125},{"pulse":90,"rpm":53,"speed":188,"distance":10,"requestedPower":135,"energy":54,"actualPower":132,"time":124},{"pulse":90,"rpm":53,"speed":188,"distance":10,"requestedPower":135,"energy":54,"actualPower":135,"time":123},{"pulse":90,"rpm":53,"speed":188,"distance":10,"requestedPower":135,"energy":54,"actualPower":135,"time":122},{"pulse":90,"rpm":48,"speed":170,"distance":10,"requestedPower":135,"energy":55,"actualPower":135,"time":121},{"pulse":90,"rpm":48,"speed":170,"distance":10,"requestedPower":135,"energy":55,"actualPower":135,"time":120},{"pulse":90,"rpm":42,"speed":149,"distance":11,"requestedPower":135,"energy":56,"actualPower":135,"time":119},{"pulse":90,"rpm":42,"speed":149,"distance":11,"requestedPower":155,"energy":56,"actualPower":135,"time":118},{"pulse":90,"rpm":42,"speed":149,"distance":11,"requestedPower":155,"energy":57,"actualPower":155,"time":117},{"pulse":90,"rpm":42,"speed":149,"distance":11,"requestedPower":155,"energy":58,"actualPower":155,"time":116},{"pulse":90,"rpm":42,"speed":149,"distance":11,"requestedPower":155,"energy":58,"actualPower":155,"time":115},{"pulse":90,"rpm":38,"speed":135,"distance":11,"requestedPower":155,"energy":59,"actualPower":155,"time":114},{"pulse":90,"rpm":38,"speed":135,"distance":11,"requestedPower":155,"energy":59,"actualPower":155,"time":113},{"pulse":90,"rpm":39,"speed":138,"distance":11,"requestedPower":155,"energy":60,"actualPower":155,"time":112},{"pulse":90,"rpm":39,"speed":138,"distance":11,"requestedPower":155,"energy":61,"actualPower":155,"time":111},{"pulse":90,"rpm":40,"speed":142,"distance":11,"requestedPower":155,"energy":61,"actualPower":155,"time":110},{"pulse":90,"rpm":40,"speed":142,"distance":11,"requestedPower":155,"energy":62,"actualPower":155,"time":109},{"pulse":90,"rpm":45,"speed":160,"distance":11,"requestedPower":155,"energy":63,"actualPower":155,"time":108},{"pulse":90,"rpm":45,"speed":160,"distance":11,"requestedPower":155,"energy":63,"actualPower":155,"time":107},{"pulse":90,"rpm":46,"speed":163,"distance":11,"requestedPower":155,"energy":64,"actualPower":155,"time":106},{"pulse":90,"rpm":46,"speed":163,"distance":11,"requestedPower":155,"energy":64,"actualPower":155,"time":105},{"pulse":90,"rpm":50,"speed":178,"distance":11,"requestedPower":155,"energy":65,"actualPower":155,"time":104},{"pulse":91,"rpm":50,"speed":178,"distance":11,"requestedPower":155,"energy":66,"actualPower":155,"time":103},{"pulse":91,"rpm":52,"speed":185,"distance":11,"requestedPower":155,"energy":66,"actualPower":155,"time":102},{"pulse":91,"rpm":52,"speed":185,"distance":11,"requestedPower":155,"energy":67,"actualPower":155,"time":101},{"pulse":91,"rpm":56,"speed":199,"distance":11,"requestedPower":155,"energy":67,"actualPower":155,"time":100},{"pulse":91,"rpm":56,"speed":199,"distance":11,"requestedPower":155,"energy":68,"actualPower":155,"time":99},{"pulse":92,"rpm":57,"speed":202,"distance":11,"requestedPower":155,"energy":69,"actualPower":155,"time":98},{"pulse":93,"rpm":57,"speed":202,"distance":12,"requestedPower":155,"energy":69,"actualPower":155,"time":97},{"pulse":94,"rpm":57,"speed":202,"distance":12,"requestedPower":155,"energy":70,"actualPower":155,"time":96},{"pulse":95,"rpm":51,"speed":181,"distance":12,"requestedPower":155,"energy":71,"actualPower":155,"time":95},{"pulse":96,"rpm":51,"speed":181,"distance":12,"requestedPower":155,"energy":71,"actualPower":155,"time":94},{"pulse":96,"rpm":51,"speed":181,"distance":12,"requestedPower":155,"energy":72,"actualPower":155,"time":93},{"pulse":96,"rpm":51,"speed":181,"distance":12,"requestedPower":155,"energy":72,"actualPower":155,"time":92},{"pulse":96,"rpm":55,"speed":195,"distance":12,"requestedPower":155,"energy":73,"actualPower":155,"time":91},{"pulse":97,"rpm":55,"speed":195,"distance":12,"requestedPower":155,"energy":74,"actualPower":155,"time":90},{"pulse":97,"rpm":57,"speed":202,"distance":12,"requestedPower":155,"energy":74,"actualPower":155,"time":89},{"pulse":97,"rpm":57,"speed":202,"distance":12,"requestedPower":155,"energy":75,"actualPower":155,"time":88},{"pulse":97,"rpm":58,"speed":206,"distance":12,"requestedPower":180,"energy":76,"actualPower":158,"time":87},{"pulse":98,"rpm":58,"speed":206,"distance":12,"requestedPower":180,"energy":76,"actualPower":180,"time":86},{"pulse":101,"rpm":54,"speed":192,"distance":12,"requestedPower":180,"energy":77,"actualPower":180,"time":85},{"pulse":101,"rpm":54,"speed":192,"distance":12,"requestedPower":180,"energy":78,"actualPower":180,"time":84},{"pulse":102,"rpm":55,"speed":195,"distance":12,"requestedPower":180,"energy":78,"actualPower":180,"time":83},{"pulse":102,"rpm":55,"speed":195,"distance":12,"requestedPower":180,"energy":79,"actualPower":180,"time":82},{"pulse":102,"rpm":49,"speed":174,"distance":12,"requestedPower":180,"energy":80,"actualPower":180,"time":81},{"pulse":102,"rpm":49,"speed":174,"distance":12,"requestedPower":180,"energy":81,"actualPower":180,"time":80},{"pulse":102,"rpm":50,"speed":178,"distance":12,"requestedPower":180,"energy":81,"actualPower":180,"time":79},{"pulse":102,"rpm":50,"speed":178,"distance":13,"requestedPower":180,"energy":82,"actualPower":180,"time":78},{"pulse":102,"rpm":50,"speed":178,"distance":13,"requestedPower":180,"energy":83,"actualPower":180,"time":77},{"pulse":102,"rpm":52,"speed":185,"distance":13,"requestedPower":180,"energy":83,"actualPower":180,"time":76},{"pulse":0,"rpm":52,"speed":185,"distance":13,"requestedPower":180,"energy":84,"actualPower":180,"time":75},{"pulse":0,"rpm":56,"speed":199,"distance":13,"requestedPower":180,"energy":85,"actualPower":180,"time":74},{"pulse":0,"rpm":56,"speed":199,"distance":13,"requestedPower":180,"energy":86,"actualPower":180,"time":73},{"pulse":0,"rpm":59,"speed":209,"distance":13,"requestedPower":180,"energy":86,"actualPower":180,"time":72},{"pulse":0,"rpm":59,"speed":209,"distance":13,"requestedPower":180,"energy":87,"actualPower":180,"time":71},{"pulse":0,"rpm":60,"speed":213,"distance":13,"requestedPower":180,"energy":88,"actualPower":180,"time":70},{"pulse":0,"rpm":60,"speed":213,"distance":13,"requestedPower":180,"energy":89,"actualPower":180,"time":69},{"pulse":0,"rpm":55,"speed":195,"distance":13,"requestedPower":180,"energy":89,"actualPower":180,"time":68},{"pulse":0,"rpm":55,"speed":195,"distance":13,"requestedPower":180,"energy":90,"actualPower":180,"time":67},{"pulse":0,"rpm":69,"speed":245,"distance":13,"requestedPower":180,"energy":91,"actualPower":180,"time":66},{"pulse":0,"rpm":69,"speed":245,"distance":13,"requestedPower":180,"energy":91,"actualPower":180,"time":65},{"pulse":0,"rpm":67,"speed":238,"distance":13,"requestedPower":180,"energy":92,"actualPower":180,"time":64},{"pulse":0,"rpm":67,"speed":238,"distance":13,"requestedPower":180,"energy":93,"actualPower":180,"time":63},{"pulse":0,"rpm":68,"speed":241,"distance":13,"requestedPower":180,"energy":94,"actualPower":180,"time":62},{"pulse":0,"rpm":68,"speed":241,"distance":14,"requestedPower":180,"energy":94,"actualPower":180,"time":61},{"pulse":0,"rpm":69,"speed":245,"distance":14,"requestedPower":180,"energy":95,"actualPower":180,"time":60},{"pulse":0,"rpm":69,"speed":245,"distance":14,"requestedPower":180,"energy":96,"actualPower":180,"time":59},{"pulse":0,"rpm":69,"speed":245,"distance":14,"requestedPower":180,"energy":96,"actualPower":180,"time":58},{"pulse":0,"rpm":69,"speed":245,"distance":14,"requestedPower":180,"energy":97,"actualPower":180,"time":57},{"pulse":0,"rpm":75,"speed":266,"distance":14,"requestedPower":200,"energy":98,"actualPower":180,"time":56},{"pulse":0,"rpm":75,"speed":266,"distance":14,"requestedPower":200,"energy":99,"actualPower":200,"time":55},{"pulse":0,"rpm":74,"speed":263,"distance":14,"requestedPower":200,"energy":99,"actualPower":200,"time":54},{"pulse":0,"rpm":74,"speed":263,"distance":14,"requestedPower":200,"energy":100,"actualPower":200,"time":53},{"pulse":0,"rpm":68,"speed":241,"distance":14,"requestedPower":200,"energy":101,"actualPower":200,"time":52},{"pulse":0,"rpm":68,"speed":241,"distance":14,"requestedPower":200,"energy":102,"actualPower":200,"time":51},{"pulse":0,"rpm":68,"speed":241,"distance":14,"requestedPower":200,"energy":103,"actualPower":200,"time":50},{"pulse":0,"rpm":77,"speed":273,"distance":14,"requestedPower":200,"energy":103,"actualPower":200,"time":49},{"pulse":0,"rpm":77,"speed":273,"distance":14,"requestedPower":200,"energy":104,"actualPower":200,"time":48},{"pulse":0,"rpm":77,"speed":273,"distance":15,"requestedPower":200,"energy":105,"actualPower":200,"time":47},{"pulse":0,"rpm":77,"speed":273,"distance":15,"requestedPower":200,"energy":106,"actualPower":200,"time":46},{"pulse":0,"rpm":82,"speed":291,"distance":15,"requestedPower":200,"energy":107,"actualPower":200,"time":45},{"pulse":0,"rpm":82,"speed":291,"distance":15,"requestedPower":200,"energy":107,"actualPower":200,"time":44},{"pulse":0,"rpm":91,"speed":323,"distance":15,"requestedPower":200,"energy":108,"actualPower":200,"time":43},{"pulse":0,"rpm":91,"speed":323,"distance":15,"requestedPower":200,"energy":109,"actualPower":200,"time":42},{"pulse":0,"rpm":95,"speed":337,"distance":15,"requestedPower":200,"energy":110,"actualPower":200,"time":41},{"pulse":0,"rpm":95,"speed":337,"distance":15,"requestedPower":200,"energy":111,"actualPower":200,"time":40},{"pulse":0,"rpm":90,"speed":320,"distance":15,"requestedPower":200,"energy":111,"actualPower":200,"time":39},{"pulse":0,"rpm":90,"speed":320,"distance":15,"requestedPower":200,"energy":112,"actualPower":200,"time":38},{"pulse":0,"rpm":88,"speed":312,"distance":15,"requestedPower":200,"energy":113,"actualPower":200,"time":37},{"pulse":0,"rpm":88,"speed":312,"distance":15,"requestedPower":200,"energy":114,"actualPower":200,"time":36},{"pulse":0,"rpm":80,"speed":284,"distance":16,"requestedPower":200,"energy":115,"actualPower":200,"time":35},{"pulse":0,"rpm":80,"speed":284,"distance":16,"requestedPower":200,"energy":115,"actualPower":200,"time":34},{"pulse":113,"rpm":78,"speed":277,"distance":16,"requestedPower":200,"energy":116,"actualPower":200,"time":33},{"pulse":114,"rpm":78,"speed":277,"distance":16,"requestedPower":200,"energy":117,"actualPower":200,"time":32},{"pulse":114,"rpm":79,"speed":280,"distance":16,"requestedPower":200,"energy":118,"actualPower":200,"time":31},{"pulse":114,"rpm":79,"speed":280,"distance":16,"requestedPower":200,"energy":119,"actualPower":200,"time":30},{"pulse":114,"rpm":79,"speed":280,"distance":16,"requestedPower":200,"energy":119,"actualPower":200,"time":29},{"pulse":0,"rpm":79,"speed":280,"distance":16,"requestedPower":200,"energy":120,"actualPower":200,"time":28},{"pulse":0,"rpm":82,"speed":291,"distance":16,"requestedPower":200,"energy":121,"actualPower":200,"time":27},{"pulse":0,"rpm":82,"speed":291,"distance":16,"requestedPower":200,"energy":122,"actualPower":200,"time":26},{"pulse":0,"rpm":82,"speed":291,"distance":16,"requestedPower":225,"energy":123,"actualPower":200,"time":25},{"pulse":0,"rpm":82,"speed":291,"distance":16,"requestedPower":225,"energy":124,"actualPower":225,"time":24},{"pulse":0,"rpm":82,"speed":291,"distance":17,"requestedPower":225,"energy":124,"actualPower":225,"time":23},{"pulse":0,"rpm":82,"speed":291,"distance":17,"requestedPower":225,"energy":125,"actualPower":225,"time":22},{"pulse":0,"rpm":87,"speed":309,"distance":17,"requestedPower":225,"energy":126,"actualPower":225,"time":21},{"pulse":0,"rpm":87,"speed":309,"distance":17,"requestedPower":225,"energy":127,"actualPower":225,"time":20},{"pulse":0,"rpm":92,"speed":327,"distance":17,"requestedPower":225,"energy":128,"actualPower":225,"time":19},{"pulse":114,"rpm":92,"speed":327,"distance":17,"requestedPower":225,"energy":129,"actualPower":225,"time":18},{"pulse":114,"rpm":92,"speed":327,"distance":17,"requestedPower":225,"energy":130,"actualPower":225,"time":17},{"pulse":114,"rpm":92,"speed":327,"distance":17,"requestedPower":225,"energy":131,"actualPower":225,"time":16},{"pulse":116,"rpm":92,"speed":327,"distance":17,"requestedPower":225,"energy":132,"actualPower":225,"time":15},{"pulse":119,"rpm":93,"speed":330,"distance":17,"requestedPower":225,"energy":133,"actualPower":225,"time":14},{"pulse":118,"rpm":93,"speed":330,"distance":17,"requestedPower":225,"energy":133,"actualPower":225,"time":13},{"pulse":119,"rpm":95,"speed":337,"distance":17,"requestedPower":225,"energy":134,"actualPower":225,"time":12},{"pulse":118,"rpm":95,"speed":337,"distance":18,"requestedPower":225,"energy":135,"actualPower":225,"time":11},{"pulse":118,"rpm":91,"speed":323,"distance":18,"requestedPower":225,"energy":136,"actualPower":225,"time":10},{"pulse":117,"rpm":91,"speed":323,"distance":18,"requestedPower":225,"energy":137,"actualPower":225,"time":9},{"pulse":117,"rpm":87,"speed":309,"distance":18,"requestedPower":225,"energy":138,"actualPower":225,"time":8},{"pulse":117,"rpm":87,"speed":309,"distance":18,"requestedPower":225,"energy":139,"actualPower":225,"time":7},{"pulse":117,"rpm":88,"speed":312,"distance":18,"requestedPower":225,"energy":140,"actualPower":225,"time":6},{"pulse":117,"rpm":88,"speed":312,"distance":18,"requestedPower":225,"energy":141,"actualPower":225,"time":5}]}]},{"naam":"Paul de Mast","meetsessies":[{"datum":"2015-11-04T13:40:39.0353176+01:00","leeftijd":48,"gewicht":66,"session":[{"pulse":0,"rpm":76,"speed":270,"distance":0,"requestedPower":50,"energy":0,"actualPower":15,"time":59},{"pulse":0,"rpm":76,"speed":270,"distance":0,"requestedPower":50,"energy":0,"actualPower":45,"time":58},{"pulse":0,"rpm":82,"speed":291,"distance":0,"requestedPower":50,"energy":0,"actualPower":50,"time":57},{"pulse":0,"rpm":82,"speed":291,"distance":0,"requestedPower":50,"energy":0,"actualPower":50,"time":56},{"pulse":0,"rpm":76,"speed":270,"distance":0,"requestedPower":50,"energy":1,"actualPower":50,"time":55},{"pulse":0,"rpm":76,"speed":270,"distance":0,"requestedPower":50,"energy":1,"actualPower":50,"time":54},{"pulse":0,"rpm":64,"speed":227,"distance":0,"requestedPower":50,"energy":1,"actualPower":50,"time":53},{"pulse":0,"rpm":64,"speed":227,"distance":0,"requestedPower":60,"energy":1,"actualPower":50,"time":52},{"pulse":0,"rpm":53,"speed":188,"distance":0,"requestedPower":60,"energy":1,"actualPower":60,"time":51},{"pulse":0,"rpm":53,"speed":188,"distance":0,"requestedPower":60,"energy":2,"actualPower":60,"time":50},{"pulse":0,"rpm":58,"speed":206,"distance":0,"requestedPower":60,"energy":2,"actualPower":60,"time":49},{"pulse":0,"rpm":58,"speed":206,"distance":0,"requestedPower":60,"energy":2,"actualPower":60,"time":48},{"pulse":0,"rpm":58,"speed":206,"distance":0,"requestedPower":60,"energy":2,"actualPower":60,"time":47},{"pulse":0,"rpm":69,"speed":245,"distance":0,"requestedPower":60,"energy":3,"actualPower":60,"time":46},{"pulse":0,"rpm":69,"speed":245,"distance":0,"requestedPower":75,"energy":3,"actualPower":60,"time":45},{"pulse":0,"rpm":71,"speed":252,"distance":1,"requestedPower":75,"energy":3,"actualPower":75,"time":44},{"pulse":0,"rpm":71,"speed":252,"distance":1,"requestedPower":75,"energy":3,"actualPower":75,"time":43},{"pulse":0,"rpm":65,"speed":231,"distance":1,"requestedPower":75,"energy":4,"actualPower":75,"time":42},{"pulse":0,"rpm":65,"speed":231,"distance":1,"requestedPower":75,"energy":4,"actualPower":75,"time":41},{"pulse":0,"rpm":62,"speed":220,"distance":1,"requestedPower":75,"energy":4,"actualPower":75,"time":40},{"pulse":0,"rpm":62,"speed":220,"distance":1,"requestedPower":75,"energy":5,"actualPower":75,"time":39},{"pulse":0,"rpm":66,"speed":234,"distance":1,"requestedPower":85,"energy":5,"actualPower":75,"time":38},{"pulse":0,"rpm":66,"speed":234,"distance":1,"requestedPower":85,"energy":5,"actualPower":85,"time":37},{"pulse":0,"rpm":64,"speed":227,"distance":1,"requestedPower":85,"energy":6,"actualPower":85,"time":36},{"pulse":0,"rpm":64,"speed":227,"distance":1,"requestedPower":85,"energy":6,"actualPower":85,"time":35},{"pulse":0,"rpm":62,"speed":220,"distance":1,"requestedPower":85,"energy":6,"actualPower":85,"time":34},{"pulse":0,"rpm":62,"speed":220,"distance":1,"requestedPower":85,"energy":7,"actualPower":85,"time":33},{"pulse":0,"rpm":63,"speed":224,"distance":1,"requestedPower":85,"energy":7,"actualPower":85,"time":32},{"pulse":0,"rpm":63,"speed":224,"distance":1,"requestedPower":95,"energy":7,"actualPower":85,"time":31},{"pulse":0,"rpm":65,"speed":231,"distance":1,"requestedPower":95,"energy":8,"actualPower":95,"time":30},{"pulse":0,"rpm":65,"speed":231,"distance":1,"requestedPower":95,"energy":8,"actualPower":95,"time":29},{"pulse":0,"rpm":66,"speed":234,"distance":2,"requestedPower":95,"energy":8,"actualPower":95,"time":28},{"pulse":0,"rpm":66,"speed":234,"distance":2,"requestedPower":95,"energy":9,"actualPower":95,"time":27},{"pulse":0,"rpm":67,"speed":238,"distance":2,"requestedPower":95,"energy":9,"actualPower":95,"time":26},{"pulse":0,"rpm":67,"speed":238,"distance":2,"requestedPower":95,"energy":10,"actualPower":95,"time":25},{"pulse":0,"rpm":67,"speed":238,"distance":2,"requestedPower":110,"energy":10,"actualPower":95,"time":24},{"pulse":0,"rpm":67,"speed":238,"distance":2,"requestedPower":110,"energy":10,"actualPower":110,"time":23},{"pulse":0,"rpm":63,"speed":224,"distance":2,"requestedPower":110,"energy":11,"actualPower":110,"time":22},{"pulse":0,"rpm":63,"speed":224,"distance":2,"requestedPower":110,"energy":11,"actualPower":110,"time":21},{"pulse":0,"rpm":63,"speed":224,"distance":2,"requestedPower":110,"energy":12,"actualPower":110,"time":20},{"pulse":0,"rpm":66,"speed":234,"distance":2,"requestedPower":110,"energy":12,"actualPower":110,"time":19},{"pulse":0,"rpm":66,"speed":234,"distance":2,"requestedPower":110,"energy":13,"actualPower":110,"time":18},{"pulse":0,"rpm":66,"speed":234,"distance":2,"requestedPower":120,"energy":13,"actualPower":110,"time":17},{"pulse":0,"rpm":66,"speed":234,"distance":2,"requestedPower":120,"energy":13,"actualPower":120,"time":16},{"pulse":0,"rpm":62,"speed":220,"distance":2,"requestedPower":120,"energy":14,"actualPower":120,"time":15},{"pulse":0,"rpm":62,"speed":220,"distance":2,"requestedPower":120,"energy":14,"actualPower":120,"time":14},{"pulse":0,"rpm":64,"speed":227,"distance":3,"requestedPower":120,"energy":15,"actualPower":120,"time":13},{"pulse":0,"rpm":64,"speed":227,"distance":3,"requestedPower":120,"energy":15,"actualPower":120,"time":12},{"pulse":0,"rpm":65,"speed":231,"distance":3,"requestedPower":120,"energy":16,"actualPower":120,"time":11},{"pulse":0,"rpm":65,"speed":231,"distance":3,"requestedPower":135,"energy":16,"actualPower":120,"time":10},{"pulse":0,"rpm":64,"speed":227,"distance":3,"requestedPower":135,"energy":17,"actualPower":135,"time":9},{"pulse":0,"rpm":64,"speed":227,"distance":3,"requestedPower":135,"energy":17,"actualPower":135,"time":8},{"pulse":0,"rpm":62,"speed":220,"distance":3,"requestedPower":135,"energy":18,"actualPower":135,"time":7},{"pulse":0,"rpm":62,"speed":220,"distance":3,"requestedPower":135,"energy":19,"actualPower":135,"time":6},{"pulse":0,"rpm":63,"speed":224,"distance":3,"requestedPower":135,"energy":19,"actualPower":135,"time":5},{"pulse":0,"rpm":63,"speed":224,"distance":3,"requestedPower":135,"energy":20,"actualPower":135,"time":4},{"pulse":0,"rpm":62,"speed":220,"distance":3,"requestedPower":145,"energy":20,"actualPower":135,"time":3},{"pulse":0,"rpm":62,"speed":220,"distance":3,"requestedPower":145,"energy":21,"actualPower":145,"time":2},{"pulse":0,"rpm":60,"speed":213,"distance":3,"requestedPower":145,"energy":21,"actualPower":145,"time":1}]}]},{"naam":"Pieter","meetsessies":[{"datum":"2015-11-04T13:59:47.9474497+01:00","leeftijd":30,"gewicht":30,"session":[{"pulse":123,"rpm":47,"speed":167,"distance":0,"requestedPower":60,"energy":0,"actualPower":21,"time":59},{"pulse":123,"rpm":47,"speed":167,"distance":0,"requestedPower":60,"energy":0,"actualPower":51,"time":58},{"pulse":123,"rpm":71,"speed":252,"distance":0,"requestedPower":60,"energy":0,"actualPower":60,"time":57},{"pulse":123,"rpm":71,"speed":252,"distance":0,"requestedPower":60,"energy":0,"actualPower":60,"time":56},{"pulse":123,"rpm":64,"speed":227,"distance":0,"requestedPower":60,"energy":1,"actualPower":60,"time":55},{"pulse":123,"rpm":64,"speed":227,"distance":0,"requestedPower":60,"energy":1,"actualPower":60,"time":54},{"pulse":123,"rpm":59,"speed":209,"distance":0,"requestedPower":60,"energy":1,"actualPower":60,"time":53},{"pulse":122,"rpm":59,"speed":209,"distance":0,"requestedPower":75,"energy":1,"actualPower":60,"time":52},{"pulse":122,"rpm":62,"speed":220,"distance":0,"requestedPower":75,"energy":2,"actualPower":75,"time":51},{"pulse":122,"rpm":62,"speed":220,"distance":0,"requestedPower":75,"energy":2,"actualPower":75,"time":50},{"pulse":122,"rpm":59,"speed":209,"distance":0,"requestedPower":75,"energy":2,"actualPower":75,"time":49},{"pulse":122,"rpm":59,"speed":209,"distance":0,"requestedPower":75,"energy":3,"actualPower":75,"time":48},{"pulse":122,"rpm":59,"speed":209,"distance":0,"requestedPower":75,"energy":3,"actualPower":75,"time":47},{"pulse":121,"rpm":59,"speed":209,"distance":0,"requestedPower":75,"energy":3,"actualPower":75,"time":46},{"pulse":121,"rpm":59,"speed":209,"distance":0,"requestedPower":95,"energy":4,"actualPower":75,"time":45},{"pulse":121,"rpm":59,"speed":209,"distance":0,"requestedPower":95,"energy":4,"actualPower":95,"time":44},{"pulse":121,"rpm":59,"speed":209,"distance":1,"requestedPower":95,"energy":4,"actualPower":95,"time":43},{"pulse":120,"rpm":57,"speed":202,"distance":1,"requestedPower":95,"energy":5,"actualPower":95,"time":42},{"pulse":120,"rpm":57,"speed":202,"distance":1,"requestedPower":95,"energy":5,"actualPower":95,"time":41},{"pulse":120,"rpm":57,"speed":202,"distance":1,"requestedPower":95,"energy":5,"actualPower":95,"time":40},{"pulse":120,"rpm":57,"speed":202,"distance":1,"requestedPower":95,"energy":5,"actualPower":95,"time":39},{"pulse":121,"rpm":61,"speed":217,"distance":1,"requestedPower":110,"energy":6,"actualPower":95,"time":38},{"pulse":121,"rpm":61,"speed":217,"distance":1,"requestedPower":110,"energy":6,"actualPower":110,"time":37},{"pulse":121,"rpm":59,"speed":209,"distance":1,"requestedPower":110,"energy":7,"actualPower":110,"time":36},{"pulse":121,"rpm":59,"speed":209,"distance":1,"requestedPower":110,"energy":7,"actualPower":110,"time":35},{"pulse":121,"rpm":61,"speed":217,"distance":1,"requestedPower":110,"energy":8,"actualPower":110,"time":34},{"pulse":121,"rpm":61,"speed":217,"distance":1,"requestedPower":110,"energy":8,"actualPower":110,"time":33},{"pulse":121,"rpm":61,"speed":217,"distance":1,"requestedPower":110,"energy":9,"actualPower":110,"time":32},{"pulse":122,"rpm":61,"speed":217,"distance":1,"requestedPower":125,"energy":9,"actualPower":110,"time":31},{"pulse":122,"rpm":62,"speed":220,"distance":1,"requestedPower":125,"energy":10,"actualPower":125,"time":30},{"pulse":123,"rpm":62,"speed":220,"distance":1,"requestedPower":125,"energy":10,"actualPower":125,"time":29},{"pulse":123,"rpm":57,"speed":202,"distance":1,"requestedPower":125,"energy":11,"actualPower":125,"time":28},{"pulse":123,"rpm":57,"speed":202,"distance":1,"requestedPower":125,"energy":11,"actualPower":125,"time":27},{"pulse":123,"rpm":60,"speed":213,"distance":2,"requestedPower":125,"energy":12,"actualPower":125,"time":26},{"pulse":124,"rpm":60,"speed":213,"distance":2,"requestedPower":125,"energy":12,"actualPower":125,"time":25},{"pulse":124,"rpm":61,"speed":217,"distance":2,"requestedPower":145,"energy":13,"actualPower":125,"time":24},{"pulse":125,"rpm":61,"speed":217,"distance":2,"requestedPower":145,"energy":13,"actualPower":145,"time":23},{"pulse":126,"rpm":58,"speed":206,"distance":2,"requestedPower":145,"energy":14,"actualPower":145,"time":22},{"pulse":126,"rpm":58,"speed":206,"distance":2,"requestedPower":145,"energy":15,"actualPower":145,"time":21},{"pulse":127,"rpm":60,"speed":213,"distance":2,"requestedPower":145,"energy":15,"actualPower":145,"time":20},{"pulse":128,"rpm":60,"speed":213,"distance":2,"requestedPower":145,"energy":16,"actualPower":145,"time":19},{"pulse":128,"rpm":60,"speed":213,"distance":2,"requestedPower":145,"energy":16,"actualPower":145,"time":18},{"pulse":129,"rpm":58,"speed":206,"distance":2,"requestedPower":160,"energy":17,"actualPower":145,"time":17},{"pulse":129,"rpm":58,"speed":206,"distance":2,"requestedPower":160,"energy":18,"actualPower":160,"time":16},{"pulse":130,"rpm":54,"speed":192,"distance":2,"requestedPower":160,"energy":18,"actualPower":160,"time":15},{"pulse":130,"rpm":54,"speed":192,"distance":2,"requestedPower":160,"energy":19,"actualPower":160,"time":14},{"pulse":130,"rpm":58,"speed":206,"distance":2,"requestedPower":160,"energy":19,"actualPower":160,"time":13},{"pulse":131,"rpm":58,"speed":206,"distance":2,"requestedPower":160,"energy":20,"actualPower":160,"time":12},{"pulse":131,"rpm":60,"speed":213,"distance":2,"requestedPower":160,"energy":21,"actualPower":160,"time":11},{"pulse":132,"rpm":60,"speed":213,"distance":2,"requestedPower":180,"energy":21,"actualPower":160,"time":10},{"pulse":133,"rpm":59,"speed":209,"distance":2,"requestedPower":180,"energy":22,"actualPower":180,"time":9},{"pulse":133,"rpm":59,"speed":209,"distance":3,"requestedPower":180,"energy":23,"actualPower":180,"time":8},{"pulse":134,"rpm":57,"speed":202,"distance":3,"requestedPower":180,"energy":24,"actualPower":180,"time":7},{"pulse":134,"rpm":57,"speed":202,"distance":3,"requestedPower":180,"energy":24,"actualPower":180,"time":6},{"pulse":134,"rpm":55,"speed":195,"distance":3,"requestedPower":180,"energy":25,"actualPower":180,"time":5},{"pulse":134,"rpm":55,"speed":195,"distance":3,"requestedPower":180,"energy":26,"actualPower":180,"time":4},{"pulse":135,"rpm":56,"speed":199,"distance":3,"requestedPower":195,"energy":26,"actualPower":180,"time":3},{"pulse":135,"rpm":56,"speed":199,"distance":3,"requestedPower":195,"energy":27,"actualPower":195,"time":2},{"pulse":136,"rpm":59,"speed":209,"distance":3,"requestedPower":195,"energy":28,"actualPower":195,"time":1}]}]},{"naam":"Pieter","meetsessies":[{"datum":"2015-11-04T13:59:47.9474497+01:00","leeftijd":30,"gewicht":30,"session":[{"pulse":123,"rpm":47,"speed":167,"distance":0,"requestedPower":60,"energy":0,"actualPower":21,"time":59},{"pulse":123,"rpm":47,"speed":167,"distance":0,"requestedPower":60,"energy":0,"actualPower":51,"time":58},{"pulse":123,"rpm":71,"speed":252,"distance":0,"requestedPower":60,"energy":0,"actualPower":60,"time":57},{"pulse":123,"rpm":71,"speed":252,"distance":0,"requestedPower":60,"energy":0,"actualPower":60,"time":56},{"pulse":123,"rpm":64,"speed":227,"distance":0,"requestedPower":60,"energy":1,"actualPower":60,"time":55},{"pulse":123,"rpm":64,"speed":227,"distance":0,"requestedPower":60,"energy":1,"actualPower":60,"time":54},{"pulse":123,"rpm":59,"speed":209,"distance":0,"requestedPower":60,"energy":1,"actualPower":60,"time":53},{"pulse":122,"rpm":59,"speed":209,"distance":0,"requestedPower":75,"energy":1,"actualPower":60,"time":52},{"pulse":122,"rpm":62,"speed":220,"distance":0,"requestedPower":75,"energy":2,"actualPower":75,"time":51},{"pulse":122,"rpm":62,"speed":220,"distance":0,"requestedPower":75,"energy":2,"actualPower":75,"time":50},{"pulse":122,"rpm":59,"speed":209,"distance":0,"requestedPower":75,"energy":2,"actualPower":75,"time":49},{"pulse":122,"rpm":59,"speed":209,"distance":0,"requestedPower":75,"energy":3,"actualPower":75,"time":48},{"pulse":122,"rpm":59,"speed":209,"distance":0,"requestedPower":75,"energy":3,"actualPower":75,"time":47},{"pulse":121,"rpm":59,"speed":209,"distance":0,"requestedPower":75,"energy":3,"actualPower":75,"time":46},{"pulse":121,"rpm":59,"speed":209,"distance":0,"requestedPower":95,"energy":4,"actualPower":75,"time":45},{"pulse":121,"rpm":59,"speed":209,"distance":0,"requestedPower":95,"energy":4,"actualPower":95,"time":44},{"pulse":121,"rpm":59,"speed":209,"distance":1,"requestedPower":95,"energy":4,"actualPower":95,"time":43},{"pulse":120,"rpm":57,"speed":202,"distance":1,"requestedPower":95,"energy":5,"actualPower":95,"time":42},{"pulse":120,"rpm":57,"speed":202,"distance":1,"requestedPower":95,"energy":5,"actualPower":95,"time":41},{"pulse":120,"rpm":57,"speed":202,"distance":1,"requestedPower":95,"energy":5,"actualPower":95,"time":40},{"pulse":120,"rpm":57,"speed":202,"distance":1,"requestedPower":95,"energy":5,"actualPower":95,"time":39},{"pulse":121,"rpm":61,"speed":217,"distance":1,"requestedPower":110,"energy":6,"actualPower":95,"time":38},{"pulse":121,"rpm":61,"speed":217,"distance":1,"requestedPower":110,"energy":6,"actualPower":110,"time":37},{"pulse":121,"rpm":59,"speed":209,"distance":1,"requestedPower":110,"energy":7,"actualPower":110,"time":36},{"pulse":121,"rpm":59,"speed":209,"distance":1,"requestedPower":110,"energy":7,"actualPower":110,"time":35},{"pulse":121,"rpm":61,"speed":217,"distance":1,"requestedPower":110,"energy":8,"actualPower":110,"time":34},{"pulse":121,"rpm":61,"speed":217,"distance":1,"requestedPower":110,"energy":8,"actualPower":110,"time":33},{"pulse":121,"rpm":61,"speed":217,"distance":1,"requestedPower":110,"energy":9,"actualPower":110,"time":32},{"pulse":122,"rpm":61,"speed":217,"distance":1,"requestedPower":125,"energy":9,"actualPower":110,"time":31},{"pulse":122,"rpm":62,"speed":220,"distance":1,"requestedPower":125,"energy":10,"actualPower":125,"time":30},{"pulse":123,"rpm":62,"speed":220,"distance":1,"requestedPower":125,"energy":10,"actualPower":125,"time":29},{"pulse":123,"rpm":57,"speed":202,"distance":1,"requestedPower":125,"energy":11,"actualPower":125,"time":28},{"pulse":123,"rpm":57,"speed":202,"distance":1,"requestedPower":125,"energy":11,"actualPower":125,"time":27},{"pulse":123,"rpm":60,"speed":213,"distance":2,"requestedPower":125,"energy":12,"actualPower":125,"time":26},{"pulse":124,"rpm":60,"speed":213,"distance":2,"requestedPower":125,"energy":12,"actualPower":125,"time":25},{"pulse":124,"rpm":61,"speed":217,"distance":2,"requestedPower":145,"energy":13,"actualPower":125,"time":24},{"pulse":125,"rpm":61,"speed":217,"distance":2,"requestedPower":145,"energy":13,"actualPower":145,"time":23},{"pulse":126,"rpm":58,"speed":206,"distance":2,"requestedPower":145,"energy":14,"actualPower":145,"time":22},{"pulse":126,"rpm":58,"speed":206,"distance":2,"requestedPower":145,"energy":15,"actualPower":145,"time":21},{"pulse":127,"rpm":60,"speed":213,"distance":2,"requestedPower":145,"energy":15,"actualPower":145,"time":20},{"pulse":128,"rpm":60,"speed":213,"distance":2,"requestedPower":145,"energy":16,"actualPower":145,"time":19},{"pulse":128,"rpm":60,"speed":213,"distance":2,"requestedPower":145,"energy":16,"actualPower":145,"time":18},{"pulse":129,"rpm":58,"speed":206,"distance":2,"requestedPower":160,"energy":17,"actualPower":145,"time":17},{"pulse":129,"rpm":58,"speed":206,"distance":2,"requestedPower":160,"energy":18,"actualPower":160,"time":16},{"pulse":130,"rpm":54,"speed":192,"distance":2,"requestedPower":160,"energy":18,"actualPower":160,"time":15},{"pulse":130,"rpm":54,"speed":192,"distance":2,"requestedPower":160,"energy":19,"actualPower":160,"time":14},{"pulse":130,"rpm":58,"speed":206,"distance":2,"requestedPower":160,"energy":19,"actualPower":160,"time":13},{"pulse":131,"rpm":58,"speed":206,"distance":2,"requestedPower":160,"energy":20,"actualPower":160,"time":12},{"pulse":131,"rpm":60,"speed":213,"distance":2,"requestedPower":160,"energy":21,"actualPower":160,"time":11},{"pulse":132,"rpm":60,"speed":213,"distance":2,"requestedPower":180,"energy":21,"actualPower":160,"time":10},{"pulse":133,"rpm":59,"speed":209,"distance":2,"requestedPower":180,"energy":22,"actualPower":180,"time":9},{"pulse":133,"rpm":59,"speed":209,"distance":3,"requestedPower":180,"energy":23,"actualPower":180,"time":8},{"pulse":134,"rpm":57,"speed":202,"distance":3,"requestedPower":180,"energy":24,"actualPower":180,"time":7},{"pulse":134,"rpm":57,"speed":202,"distance":3,"requestedPower":180,"energy":24,"actualPower":180,"time":6},{"pulse":134,"rpm":55,"speed":195,"distance":3,"requestedPower":180,"energy":25,"actualPower":180,"time":5},{"pulse":134,"rpm":55,"speed":195,"distance":3,"requestedPower":180,"energy":26,"actualPower":180,"time":4},{"pulse":135,"rpm":56,"speed":199,"distance":3,"requestedPower":195,"energy":26,"actualPower":180,"time":3},{"pulse":135,"rpm":56,"speed":199,"distance":3,"requestedPower":195,"energy":27,"actualPower":195,"time":2},{"pulse":136,"rpm":59,"speed":209,"distance":3,"requestedPower":195,"energy":28,"actualPower":195,"time":1}]}]}]